__init__.py
tiptoidl.py
tiptoi_dl-0.1.0.dist-info/METADATA
tiptoi_dl-0.1.0.dist-info/WHEEL
tiptoi_dl-0.1.0.dist-info/entry_points.txt
tiptoi_dl-0.1.0.dist-info/top_level.txt
tiptoi_dl-0.1.0.dist-info/RECORD
