Metadata-Version: 2.1
Name: tiptoi-dl
Version: 0.1.0
Summary: A TipToi Download helper
Requires-Python: >=3.13
Requires-Dist: beautifulsoup4>=4.12.3
Requires-Dist: requests>=2.32.3
Requires-Dist: tqdm>=4.67.1
